{
    "name": "Backup Power",
    "version": {
        "major": 1,
        "minor": 3,
        "build": 52
    },
    "git_user": "fluffy-mods",
    "git_repo": "BackupPower",
    "visibility": 0,
    "packageId": "fluffy.backuppower",
    "changenote": "",
    "changenotes": [
        {
            "repo": "BackupPower",
            "hash": "5453e9029010379e57420beb6fd4344f8b55c835",
            "date": "2020-05-04 23:05",
            "author": "Fluffy",
            "message": "Release 1.3.52 [nolog]"
        }
    ],
    "contributors": {
        "Cenbes": "Control box texture"
    },
    "tags": [
        "1.1"
    ],
    "publishedfileid": "2084493662"
}